LICENSE
README.rst
pyproject.toml
setup.cfg
setup.py
src/biocatalyzer/__init__.py
src/biocatalyzer/_utils.py
src/biocatalyzer/bioreactor.py
src/biocatalyzer/matcher.py
src/biocatalyzer.egg-info/PKG-INFO
src/biocatalyzer.egg-info/SOURCES.txt
src/biocatalyzer.egg-info/dependency_links.txt
src/biocatalyzer.egg-info/entry_points.txt
src/biocatalyzer.egg-info/not-zip-safe
src/biocatalyzer.egg-info/requires.txt
src/biocatalyzer.egg-info/top_level.txt
src/biocatalyzer/chem/__init__.py
src/biocatalyzer/chem/_utils.py
src/biocatalyzer/chem/chem_utils.py
src/biocatalyzer/clis/__init__.py
src/biocatalyzer/clis/cli.py
src/biocatalyzer/clis/cli_bioreactor.py
src/biocatalyzer/clis/cli_matcher.py
src/biocatalyzer/data/byproducts_to_remove/byproducts.tsv
src/biocatalyzer/data/patterns_to_remove/patterns.tsv
src/biocatalyzer/data/reactionrules/all_reaction_rules_forward_no_smarts_duplicates_sample.tsv
src/biocatalyzer/io_utils/__init__.py
src/biocatalyzer/io_utils/loaders.py