Metadata-Version: 2.1
Name: biocatalyzer
Version: 0.0.4b0
Summary: BioCatalyzer: a rule-based tool to predict compound metabolism
Home-page: https://github.com/jcorreia11/BioCatalyzer
Author: João Correia
Author-email: jfscorreia95@gmail.com
License: MIT
Download-URL: https://github.com/jcorreia11/BioCatalyzer/archive/refs/tags/v0.0.4-beta.tar.gz
Keywords: reaction-rules,metabolism,enzymatic-reactions,chemoinformatics,cheminformatics
Platform: unix
Platform: linux
Platform: osx
Platform: cygwin
Platform: win32
Classifier: Development Status :: 4 - Beta
Classifier: License :: OSI Approved :: MIT License
Classifier: Programming Language :: Python :: 3.7
Classifier: Programming Language :: Python :: 3.8
Requires-Python: >=3.7
Provides-Extra: testing
License-File: LICENSE
